grow/__init__.py
grow/moisture.py
grow/pump.py
growhat-0.0.3.dist-info/LICENSE.txt
growhat-0.0.3.dist-info/METADATA
growhat-0.0.3.dist-info/WHEEL
growhat-0.0.3.dist-info/top_level.txt
growhat-0.0.3.dist-info/RECORD
