Metadata-Version: 2.1
Name: growhat
Version: 0.0.3
Summary: Grow HAT Mini. A plant valet add-on for the Raspberry Pi
Home-page: https://www.pimoroni.com
Author: Philip Howard, Paul Beech
Author-email: phil@pimoroni.com
License: MIT
Project-URL: GitHub, https://www.github.com/pimoroni/grow-python
Keywords: Raspberry Pi
Classifier: Development Status :: 4 - Beta
Classifier: Operating System :: POSIX :: Linux
Classifier: License :: OSI Approved :: MIT License
Classifier: Intended Audience :: Developers
Classifier: Programming Language :: Python :: 3
Classifier: Topic :: Software Development
Classifier: Topic :: Software Development :: Libraries
Classifier: Topic :: System :: Hardware
Requires-Python: >=3
License-File: LICENSE.txt
Requires-Dist: font-roboto
Requires-Dist: fonts
Requires-Dist: ltr559 (==0.1.1)
Requires-Dist: pyyaml
Requires-Dist: st7735 (==0.0.5)
